bd_isssteson/__init__.py
bd_isssteson/encriptaciones.py
bd_isssteson/funciones.py
bd_isssteson/globales.py
datos_BD-2.1.9.dist-info/LICENSE
datos_BD-2.1.9.dist-info/METADATA
datos_BD-2.1.9.dist-info/WHEEL
datos_BD-2.1.9.dist-info/top_level.txt
datos_BD-2.1.9.dist-info/RECORD
