Metadata-Version: 2.1
Name: datos_BD
Version: 2.1.9
Summary: Librería para acceder a los Datos de conexión a servidores del Instituto de Seguridad y Servicios Sociales de los Trabajadores del Estado de Sonora (ISSSTESON).
Author: Alan Adalberto Ortiz Pérez
Author-email: aortiz@isssteson.gob.mx
License: © 2024 ISSSTESON
License-File: LICENSE
Requires-Dist: pycryptodome
